CHANGES.txt
Makefile
README.txt
setup.py
haufe/__init__.py
haufe.testrunner.egg-info/PKG-INFO
haufe.testrunner.egg-info/SOURCES.txt
haufe.testrunner.egg-info/dependency_links.txt
haufe.testrunner.egg-info/entry_points.txt
haufe.testrunner.egg-info/namespace_packages.txt
haufe.testrunner.egg-info/not-zip-safe
haufe.testrunner.egg-info/requires.txt
haufe.testrunner.egg-info/top_level.txt
haufe/testrunner/__init__.py
haufe/testrunner/cli.py
haufe/testrunner/formatter.py
haufe/testrunner/sample-testrunner.ini
haufe/testrunner/styles.py
haufe/testrunner/database/__init__.py
haufe/testrunner/database/bootstrap.py
haufe/testrunner/database/config.py
haufe/testrunner/database/model.py
haufe/testrunner/database/setup.py
haufe/testrunner/styles/report.css
haufe/testrunner/tests/__init__.py