Metadata-Version: 1.0
Name: haufe.testrunner
Version: 0.5.6.2
Summary: A wrapper for the Zope testrunner providing email support, HTML generation and RSS support
Home-page: ????
Author: Andreas Jung
Author-email: andreas.jung@haufe.de
License: n/a
Platform: UNKNOWN
Classifier: Programming Language :: Python
